nodemodel/__init__.py
nodemodel/graph_functions.py
nodemodel/helpers.py
nodemodel/model.py
nodemodel/node.py
nodemodel/utils.py
nodemodel-0.1.5.dist-info/LICENSE
nodemodel-0.1.5.dist-info/METADATA
nodemodel-0.1.5.dist-info/WHEEL
nodemodel-0.1.5.dist-info/top_level.txt
nodemodel-0.1.5.dist-info/RECORD
